veolint/__init__.py
veolint/plugin.py
veolint-0.1.dist-info/LICENSE
veolint-0.1.dist-info/METADATA
veolint-0.1.dist-info/WHEEL
veolint-0.1.dist-info/entry_points.txt
veolint-0.1.dist-info/top_level.txt
veolint-0.1.dist-info/RECORD
